LICENSE
MANIFEST.in
README.md
requirements.txt
setup.py
gae/__about__.py
gae/__init__.py
gae/link_libs/__init__.py
gae/link_libs/__main__.py
gae/link_libs/base.py
gae/link_libs/pip.py
gae/link_libs/pipfile.py
gae_utils.egg-info/PKG-INFO
gae_utils.egg-info/SOURCES.txt
gae_utils.egg-info/dependency_links.txt
gae_utils.egg-info/entry_points.txt
gae_utils.egg-info/namespace_packages.txt
gae_utils.egg-info/requires.txt
gae_utils.egg-info/top_level.txt