Metadata-Version: 1.2
Name: gae-utils
Version: 1.0.0
Summary: Utility to help tame python dependencies with Google AppEngine Standard
Home-page: https://github.com/RealKinetic/gae-utils
Maintainer: Nick Joyce
Maintainer-email: nick.joyce@realkinetic.com
License: UNKNOWN
Platform: UNKNOWN
